temi/__init__.py
temi/api.py
temi-0.0.2.dist-info/LICENSE
temi-0.0.2.dist-info/METADATA
temi-0.0.2.dist-info/WHEEL
temi-0.0.2.dist-info/top_level.txt
temi-0.0.2.dist-info/RECORD
