Metadata-Version: 2.1
Name: temi
Version: 0.0.2
Summary: (Unofficial) Python library for remote-controlling the Temi robot, via WebSocket.
Home-page: https://github.com/tongji-cdi/temi
Author: Shengchen Zhang
Author-email: shengchenzhang1207@gmail.com
License: UNKNOWN
Project-URL: Bug Tracker, https://github.com/tongji-cdi/temi/issues
Platform: UNKNOWN
Classifier: Programming Language :: Python :: 3
Classifier: License :: OSI Approved :: MIT License
Classifier: Operating System :: OS Independent
Requires-Python: >=3.6
License-File: LICENSE
